dvag_mon_shared/AzureCredentials.py
dvag_mon_shared/KqlClasses.py
dvag_mon_shared/PushgwHeartbeat.py
dvag_mon_shared/__init__.py
dvag_mon_shared/mapping_const.py
dvag_mon_shared-1.0.5.dist-info/LICENSE
dvag_mon_shared-1.0.5.dist-info/METADATA
dvag_mon_shared-1.0.5.dist-info/WHEEL
dvag_mon_shared-1.0.5.dist-info/top_level.txt
dvag_mon_shared-1.0.5.dist-info/RECORD
