Metadata-Version: 2.1
Name: dvag-mon-shared
Version: 1.0.5
Summary: infra-monitoring-functions shared libraries
Author-email: Team Monitoring <monitoring@dvag.com>
Project-URL: Github, https://github.com/dvag/infra-monitoring-functions
Classifier: Programming Language :: Python :: 3
Classifier: License :: OSI Approved :: MIT License
Classifier: Operating System :: OS Independent
Requires-Python: >=3.7
License-File: LICENSE
Requires-Dist: azure-identity
Requires-Dist: azure-core
Requires-Dist: azure-keyvault-secrets
Requires-Dist: azure-monitor-query
Requires-Dist: DateTime
Requires-Dist: pandas
Requires-Dist: prometheus-client
Requires-Dist: dataclasses
Requires-Dist: python-dateutil
Requires-Dist: pytimeparse
Requires-Dist: azure-storage-blob
